[

  {
    "model": "EvPresentaciones.usuario",
    "pk": "eval1@eval.cl",
    "fields": {
      "nombre": "Armando",
      "apellido": "Templates",
      "esAdministrador": false,
      "contrasena": "123"
    }
  },
  {
    "model": "EvPresentaciones.usuario",
    "pk": "eval2@eval.cl",
    "fields": {
      "nombre": "Armando",
      "apellido": "Plantillas",
      "esAdministrador": false,
      "contrasena": "123"
    }
  },
  {
    "model": "EvPresentaciones.usuario",
    "pk": "eval3@eval.cl",
    "fields": {
      "nombre": "Armando",
      "apellido": "Esqueletos",
      "esAdministrador": false,
      "contrasena": "123"
    }
  },
  {
    "model": "EvPresentaciones.usuario",
    "pk": "sergio@sergio.cl",
    "fields": {
      "nombre": "Sergio",
      "apellido": "Casas",
      "esAdministrador": true,
      "contrasena": "sergio"
    }
  },
  {
    "model": "EvPresentaciones.usuario",
    "pk": "valentina@valentina.cl",
    "fields": {
      "nombre": "Valentina",
      "apellido": "Paredes",
      "esAdministrador": true,
      "contrasena": "valentina"
    }
  },
  {
    "model": "EvPresentaciones.cursos",
    "pk": 1,
    "fields": {
      "nombre": "Logaritmos",
      "codigo": "CC3451",
      "semestre": "Oto\u00f1o",
      "a\u00f1o": 2018,
      "seccion": 1
    }
  },
  {
    "model": "EvPresentaciones.cursos",
    "pk": 2,
    "fields": {
      "nombre": "Ingenieria",
      "codigo": "CC3410",
      "semestre": "Oto\u00c3\u00b1o",
      "a\u00f1o": 2019,
      "seccion": 1
    }
  },
  {
    "model": "EvPresentaciones.cursos",
    "pk": 3,
    "fields": {
      "nombre": "Objecto",
      "codigo": "CC3410",
      "semestre": "Primavera",
      "a\u00f1o": 2018,
      "seccion": 1
    }
  },
  {
    "model": "EvPresentaciones.cursos",
    "pk": 4,
    "fields": {
      "nombre": "Objecto",
      "codigo": "CC3411",
      "semestre": "Primavera",
      "a\u00f1o": 2018,
      "seccion": 1
    }
  },
  {
    "model": "EvPresentaciones.alumnos",
    "pk": 1234567,
    "fields": {
      "nombre": "Armando",
      "apellido": "Botellas",
      "presento": true,
      "codigoVerificador": "2"
    }
  },
  {
    "model": "EvPresentaciones.alumnos",
    "pk": 12234567,
    "fields": {
      "nombre": "Armando",
      "apellido": "Django",
      "presento": false,
      "codigoVerificador": "0"
    }
  },
  {
    "model": "EvPresentaciones.alumnos",
    "pk": 12334567,
    "fields": {
      "nombre": "Armando",
      "apellido": "Proyectos",
      "presento": false,
      "codigoVerificador": "9"
    }
  },
  {
    "model": "EvPresentaciones.alumnos",
    "pk": 12342567,
    "fields": {
      "nombre": "Armando",
      "apellido": "Bases",
      "presento": false,
      "codigoVerificador": "5"
    }
  },
  {
    "model": "EvPresentaciones.alumnos",
    "pk": 12349567,
    "fields": {
      "nombre": "Armando",
      "apellido": "Teles",
      "presento": true,
      "codigoVerificador": "5"
    }
  },
  {
    "model": "EvPresentaciones.alumnos",
    "pk": 12384567,
    "fields": {
      "nombre": "Armando",
      "apellido": "Pelotas",
      "presento": false,
      "codigoVerificador": "8"
    }
  },
  {
    "model": "EvPresentaciones.alumnos",
    "pk": 1234521367,
    "fields": {
      "nombre": "Armando",
      "apellido": "Scripts",
      "presento": true,
      "codigoVerificador": "5"
    }
  },
  {
    "model": "EvPresentaciones.alumnos",
    "pk": 1237764567,
    "fields": {
      "nombre": "Armando",
      "apellido": "PC",
      "presento": false,
      "codigoVerificador": "3"
    }
  },
  {
    "model": "EvPresentaciones.rubrica",
    "pk": "CC4301",
    "fields": {
      "version": "Oto\u00f1o 2018",
      "tiempo": "00:00:05",
      "tiempoMin": "00:00:02",
      "archivo": "./EvPresentaciones/ArchivosRubricas\\1.csv"
    }
  },
  {
    "model": "EvPresentaciones.rubrica",
    "pk": "CC4456",
    "fields": {
      "version": "dos",
      "tiempo": "00:00:08",
      "tiempoMin": "00:00:07",
      "archivo": "./EvPresentaciones/ArchivosRubricas\\2.csv"
    }
  },
  {
    "model": "EvPresentaciones.evaluacion",
    "pk": 1,
    "fields": {
      "fechaInicio": "2019-05-14T23:37:10Z",
      "fechaTermino": "2019-05-08T23:37:13Z",
      "estado": "Abierta",
      "duracion": "00:00:08"
    }
  },
  {
    "model": "EvPresentaciones.evaluacion",
    "pk": 2,
    "fields": {
      "fechaInicio": "2019-05-19T23:37:27Z",
      "fechaTermino": "2019-05-14T00:00:00Z",
      "estado": "Abierta",
      "duracion": "00:00:06"
    }
  },
  {
    "model": "EvPresentaciones.usuario_evaluacion",
    "pk": 1,
    "fields": {
      "user": "bla@bla.cl",
      "evaluacion": 1
    }
  },
  {
    "model": "EvPresentaciones.usuario_evaluacion",
    "pk": 2,
    "fields": {
      "user": "eval1@eval.cl",
      "evaluacion": 2
    }
  },
  {
    "model": "EvPresentaciones.usuario_evaluacion",
    "pk": 3,
    "fields": {
      "user": "eval3@eval.cl",
      "evaluacion": 2
    }
  },
  {
    "model": "EvPresentaciones.evaluacion_rubrica",
    "pk": 1,
    "fields": {
      "evaluacion": 1,
      "rubrica": "CC4301"
    }
  },
  {
    "model": "EvPresentaciones.cursos_evaluacion",
    "pk": 1,
    "fields": {
      "curso": 1,
      "evaluacion": 1
    }
  },
  {
    "model": "EvPresentaciones.cursos_evaluacion",
    "pk": 2,
    "fields": {
      "curso": 2,
      "evaluacion": 2
    }
  },
  {
    "model": "EvPresentaciones.cursos_alumnos",
    "pk": 1,
    "fields": {
      "nombreGrupo": "No Group",
      "curso": 1,
      "alumnos": 12384567
    }
  },
  {
    "model": "EvPresentaciones.cursos_alumnos",
    "pk": 2,
    "fields": {
      "nombreGrupo": "fsociety",
      "curso": 3,
      "alumnos": 12342567
    }
  },
  {
    "model": "EvPresentaciones.cursos_alumnos",
    "pk": 3,
    "fields": {
      "nombreGrupo": "fsociety",
      "curso": 2,
      "alumnos": 12334567
    }
  },
  {
    "model": "EvPresentaciones.alumnos_evaluacion",
    "pk": 1,
    "fields": {
      "nota": 6.0,
      "alumno": 1234567,
      "evaluacion": 1
    }
  },
  {
    "model": "EvPresentaciones.alumnos_evaluacion",
    "pk": 2,
    "fields": {
      "nota": 8.0,
      "alumno": 12342567,
      "evaluacion": 2
    }
  },
  {
    "model": "contenttypes.contenttype",
    "pk": 1,
    "fields": {
      "app_label": "EvPresentaciones",
      "model": "usuario"
    }
  },
  {
    "model": "contenttypes.contenttype",
    "pk": 2,
    "fields": {
      "app_label": "EvPresentaciones",
      "model": "cursos"
    }
  },
  {
    "model": "contenttypes.contenttype",
    "pk": 3,
    "fields": {
      "app_label": "EvPresentaciones",
      "model": "alumnos"
    }
  },
  {
    "model": "contenttypes.contenttype",
    "pk": 4,
    "fields": {
      "app_label": "EvPresentaciones",
      "model": "rubrica"
    }
  },
  {
    "model": "contenttypes.contenttype",
    "pk": 5,
    "fields": {
      "app_label": "EvPresentaciones",
      "model": "evaluacion"
    }
  },
  {
    "model": "contenttypes.contenttype",
    "pk": 6,
    "fields": {
      "app_label": "EvPresentaciones",
      "model": "usuario_evaluacion"
    }
  },
  {
    "model": "contenttypes.contenttype",
    "pk": 7,
    "fields": {
      "app_label": "EvPresentaciones",
      "model": "evaluacion_rubrica"
    }
  },
  {
    "model": "contenttypes.contenttype",
    "pk": 8,
    "fields": {
      "app_label": "EvPresentaciones",
      "model": "cursos_evaluacion"
    }
  },
  {
    "model": "contenttypes.contenttype",
    "pk": 9,
    "fields": {
      "app_label": "EvPresentaciones",
      "model": "cursos_alumnos"
    }
  },
  {
    "model": "contenttypes.contenttype",
    "pk": 10,
    "fields": {
      "app_label": "EvPresentaciones",
      "model": "alumnos_evaluacion"
    }
  },
  {
    "model": "contenttypes.contenttype",
    "pk": 11,
    "fields": {
      "app_label": "admin",
      "model": "logentry"
    }
  },
  {
    "model": "contenttypes.contenttype",
    "pk": 12,
    "fields": {
      "app_label": "auth",
      "model": "permission"
    }
  },
  {
    "model": "contenttypes.contenttype",
    "pk": 13,
    "fields": {
      "app_label": "auth",
      "model": "group"
    }
  },
  {
    "model": "contenttypes.contenttype",
    "pk": 14,
    "fields": {
      "app_label": "auth",
      "model": "user"
    }
  },
  {
    "model": "contenttypes.contenttype",
    "pk": 15,
    "fields": {
      "app_label": "contenttypes",
      "model": "contenttype"
    }
  },
  {
    "model": "contenttypes.contenttype",
    "pk": 16,
    "fields": {
      "app_label": "sessions",
      "model": "session"
    }
  },
  {
    "model": "sessions.session",
    "pk": "md4owuaelzzqkplukhmww9g7vmw3cvti",
    "fields": {
      "session_data": "YjhmZjVmYjdjNmYxYzNmYmJmNTU3Nzg3NzcwMTcxNDY5MzlhZDM4MTp7Il9hdXRoX3VzZXJfaWQiOiIyIiwiX2F1dGhfdXNlcl9iYWNrZW5kIjoiZGphbmdvLmNvbnRyaWIuYXV0aC5iYWNrZW5kcy5Nb2RlbEJhY2tlbmQiLCJfYXV0aF91c2VyX2hhc2giOiJkNmRmZjQzZjQzNTgwYzBiZmE4MGIwMThhOWE0MWQxNTUxYTc2ODFlIn0=",
      "expire_date": "2019-05-19T23:43:14.094Z"
    }
  },
  {
    "model": "auth.permission",
    "pk": 1,
    "fields": {
      "name": "Can add usuario",
      "content_type": 1,
      "codename": "add_usuario"
    }
  },
  {
    "model": "auth.permission",
    "pk": 2,
    "fields": {
      "name": "Can change usuario",
      "content_type": 1,
      "codename": "change_usuario"
    }
  },
  {
    "model": "auth.permission",
    "pk": 3,
    "fields": {
      "name": "Can delete usuario",
      "content_type": 1,
      "codename": "delete_usuario"
    }
  },
  {
    "model": "auth.permission",
    "pk": 4,
    "fields": {
      "name": "Can add cursos",
      "content_type": 2,
      "codename": "add_cursos"
    }
  },
  {
    "model": "auth.permission",
    "pk": 5,
    "fields": {
      "name": "Can change cursos",
      "content_type": 2,
      "codename": "change_cursos"
    }
  },
  {
    "model": "auth.permission",
    "pk": 6,
    "fields": {
      "name": "Can delete cursos",
      "content_type": 2,
      "codename": "delete_cursos"
    }
  },
  {
    "model": "auth.permission",
    "pk": 7,
    "fields": {
      "name": "Can add alumnos",
      "content_type": 3,
      "codename": "add_alumnos"
    }
  },
  {
    "model": "auth.permission",
    "pk": 8,
    "fields": {
      "name": "Can change alumnos",
      "content_type": 3,
      "codename": "change_alumnos"
    }
  },
  {
    "model": "auth.permission",
    "pk": 9,
    "fields": {
      "name": "Can delete alumnos",
      "content_type": 3,
      "codename": "delete_alumnos"
    }
  },
  {
    "model": "auth.permission",
    "pk": 10,
    "fields": {
      "name": "Can add rubrica",
      "content_type": 4,
      "codename": "add_rubrica"
    }
  },
  {
    "model": "auth.permission",
    "pk": 11,
    "fields": {
      "name": "Can change rubrica",
      "content_type": 4,
      "codename": "change_rubrica"
    }
  },
  {
    "model": "auth.permission",
    "pk": 12,
    "fields": {
      "name": "Can delete rubrica",
      "content_type": 4,
      "codename": "delete_rubrica"
    }
  },
  {
    "model": "auth.permission",
    "pk": 13,
    "fields": {
      "name": "Can add evaluacion",
      "content_type": 5,
      "codename": "add_evaluacion"
    }
  },
  {
    "model": "auth.permission",
    "pk": 14,
    "fields": {
      "name": "Can change evaluacion",
      "content_type": 5,
      "codename": "change_evaluacion"
    }
  },
  {
    "model": "auth.permission",
    "pk": 15,
    "fields": {
      "name": "Can delete evaluacion",
      "content_type": 5,
      "codename": "delete_evaluacion"
    }
  },
  {
    "model": "auth.permission",
    "pk": 16,
    "fields": {
      "name": "Can add usuario_ evaluacion",
      "content_type": 6,
      "codename": "add_usuario_evaluacion"
    }
  },
  {
    "model": "auth.permission",
    "pk": 17,
    "fields": {
      "name": "Can change usuario_ evaluacion",
      "content_type": 6,
      "codename": "change_usuario_evaluacion"
    }
  },
  {
    "model": "auth.permission",
    "pk": 18,
    "fields": {
      "name": "Can delete usuario_ evaluacion",
      "content_type": 6,
      "codename": "delete_usuario_evaluacion"
    }
  },
  {
    "model": "auth.permission",
    "pk": 19,
    "fields": {
      "name": "Can add evaluacion_ rubrica",
      "content_type": 7,
      "codename": "add_evaluacion_rubrica"
    }
  },
  {
    "model": "auth.permission",
    "pk": 20,
    "fields": {
      "name": "Can change evaluacion_ rubrica",
      "content_type": 7,
      "codename": "change_evaluacion_rubrica"
    }
  },
  {
    "model": "auth.permission",
    "pk": 21,
    "fields": {
      "name": "Can delete evaluacion_ rubrica",
      "content_type": 7,
      "codename": "delete_evaluacion_rubrica"
    }
  },
  {
    "model": "auth.permission",
    "pk": 22,
    "fields": {
      "name": "Can add cursos_ evaluacion",
      "content_type": 8,
      "codename": "add_cursos_evaluacion"
    }
  },
  {
    "model": "auth.permission",
    "pk": 23,
    "fields": {
      "name": "Can change cursos_ evaluacion",
      "content_type": 8,
      "codename": "change_cursos_evaluacion"
    }
  },
  {
    "model": "auth.permission",
    "pk": 24,
    "fields": {
      "name": "Can delete cursos_ evaluacion",
      "content_type": 8,
      "codename": "delete_cursos_evaluacion"
    }
  },
  {
    "model": "auth.permission",
    "pk": 25,
    "fields": {
      "name": "Can add cursos_ alumnos",
      "content_type": 9,
      "codename": "add_cursos_alumnos"
    }
  },
  {
    "model": "auth.permission",
    "pk": 26,
    "fields": {
      "name": "Can change cursos_ alumnos",
      "content_type": 9,
      "codename": "change_cursos_alumnos"
    }
  },
  {
    "model": "auth.permission",
    "pk": 27,
    "fields": {
      "name": "Can delete cursos_ alumnos",
      "content_type": 9,
      "codename": "delete_cursos_alumnos"
    }
  },
  {
    "model": "auth.permission",
    "pk": 28,
    "fields": {
      "name": "Can add alumnos_ evaluacion",
      "content_type": 10,
      "codename": "add_alumnos_evaluacion"
    }
  },
  {
    "model": "auth.permission",
    "pk": 29,
    "fields": {
      "name": "Can change alumnos_ evaluacion",
      "content_type": 10,
      "codename": "change_alumnos_evaluacion"
    }
  },
  {
    "model": "auth.permission",
    "pk": 30,
    "fields": {
      "name": "Can delete alumnos_ evaluacion",
      "content_type": 10,
      "codename": "delete_alumnos_evaluacion"
    }
  },
  {
    "model": "auth.permission",
    "pk": 31,
    "fields": {
      "name": "Can add log entry",
      "content_type": 11,
      "codename": "add_logentry"
    }
  },
  {
    "model": "auth.permission",
    "pk": 32,
    "fields": {
      "name": "Can change log entry",
      "content_type": 11,
      "codename": "change_logentry"
    }
  },
  {
    "model": "auth.permission",
    "pk": 33,
    "fields": {
      "name": "Can delete log entry",
      "content_type": 11,
      "codename": "delete_logentry"
    }
  },
  {
    "model": "auth.permission",
    "pk": 34,
    "fields": {
      "name": "Can add permission",
      "content_type": 12,
      "codename": "add_permission"
    }
  },
  {
    "model": "auth.permission",
    "pk": 35,
    "fields": {
      "name": "Can change permission",
      "content_type": 12,
      "codename": "change_permission"
    }
  },
  {
    "model": "auth.permission",
    "pk": 36,
    "fields": {
      "name": "Can delete permission",
      "content_type": 12,
      "codename": "delete_permission"
    }
  },
  {
    "model": "auth.permission",
    "pk": 37,
    "fields": {
      "name": "Can add group",
      "content_type": 13,
      "codename": "add_group"
    }
  },
  {
    "model": "auth.permission",
    "pk": 38,
    "fields": {
      "name": "Can change group",
      "content_type": 13,
      "codename": "change_group"
    }
  },
  {
    "model": "auth.permission",
    "pk": 39,
    "fields": {
      "name": "Can delete group",
      "content_type": 13,
      "codename": "delete_group"
    }
  },
  {
    "model": "auth.permission",
    "pk": 40,
    "fields": {
      "name": "Can add user",
      "content_type": 14,
      "codename": "add_user"
    }
  },
  {
    "model": "auth.permission",
    "pk": 41,
    "fields": {
      "name": "Can change user",
      "content_type": 14,
      "codename": "change_user"
    }
  },
  {
    "model": "auth.permission",
    "pk": 42,
    "fields": {
      "name": "Can delete user",
      "content_type": 14,
      "codename": "delete_user"
    }
  },
  {
    "model": "auth.permission",
    "pk": 43,
    "fields": {
      "name": "Can add content type",
      "content_type": 15,
      "codename": "add_contenttype"
    }
  },
  {
    "model": "auth.permission",
    "pk": 44,
    "fields": {
      "name": "Can change content type",
      "content_type": 15,
      "codename": "change_contenttype"
    }
  },
  {
    "model": "auth.permission",
    "pk": 45,
    "fields": {
      "name": "Can delete content type",
      "content_type": 15,
      "codename": "delete_contenttype"
    }
  },
  {
    "model": "auth.permission",
    "pk": 46,
    "fields": {
      "name": "Can add session",
      "content_type": 16,
      "codename": "add_session"
    }
  },
  {
    "model": "auth.permission",
    "pk": 47,
    "fields": {
      "name": "Can change session",
      "content_type": 16,
      "codename": "change_session"
    }
  },
  {
    "model": "auth.permission",
    "pk": 48,
    "fields": {
      "name": "Can delete session",
      "content_type": 16,
      "codename": "delete_session"
    }
  },
  {
    "model": "auth.user",
    "pk": 1,
    "fields": {
      "password": "pbkdf2_sha256$100000$HHHDjapQ1Y8L$ry0lXWnjn6RORkDQAQay2RoeTOyMScF4F5xu2e08kV0=",
      "last_login": "2019-05-05T22:05:09.587Z",
      "is_superuser": true,
      "username": "selva",
      "first_name": "",
      "last_name": "",
      "email": "a@a.cl",
      "is_staff": true,
      "is_active": true,
      "date_joined": "2019-05-05T22:04:32.239Z",
      "groups": [],
      "user_permissions": []
    }
  },
  {
    "model": "auth.user",
    "pk": 2,
    "fields": {
      "password": "pbkdf2_sha256$100000$2LdN1cYWbXJt$uyet2VyeX50nE1QvNWE6aZUVJlT8+P29U/JgqYAfhqg=",
      "last_login": "2019-05-05T23:43:13.943Z",
      "is_superuser": true,
      "username": "dummy",
      "first_name": "",
      "last_name": "",
      "email": "a@a.cl",
      "is_staff": true,
      "is_active": true,
      "date_joined": "2019-05-05T23:42:31.761Z",
      "groups": [],
      "user_permissions": []
    }
  },
  {
    "model": "admin.logentry",
    "pk": 1,
    "fields": {
      "action_time": "2019-05-05T22:05:23.936Z",
      "user": 1,
      "content_type": 14,
      "object_id": "1",
      "object_repr": "selva",
      "action_flag": 2,
      "change_message": "[{\"changed\": {\"fields\": [\"password\"]}}]"
    }
  },
  {
    "model": "admin.logentry",
    "pk": 2,
    "fields": {
      "action_time": "2019-05-05T22:11:10.375Z",
      "user": 1,
      "content_type": 1,
      "object_id": "bla@bla.cl",
      "object_repr": "bla@bla.cl",
      "action_flag": 1,
      "change_message": "[{\"added\": {}}]"
    }
  },
  {
    "model": "admin.logentry",
    "pk": 3,
    "fields": {
      "action_time": "2019-05-05T22:38:18.215Z",
      "user": 1,
      "content_type": 2,
      "object_id": "1",
      "object_repr": "Logaritmos CC3451 Oto\u00f1o 2018 1",
      "action_flag": 1,
      "change_message": "[{\"added\": {}}]"
    }
  },
  {
    "model": "admin.logentry",
    "pk": 4,
    "fields": {
      "action_time": "2019-05-05T23:35:40.677Z",
      "user": 1,
      "content_type": 4,
      "object_id": "CC4301",
      "object_repr": "CC4301 Oto\u00f1o 2018",
      "action_flag": 1,
      "change_message": "[{\"added\": {}}]"
    }
  },
  {
    "model": "admin.logentry",
    "pk": 5,
    "fields": {
      "action_time": "2019-05-05T23:36:00.713Z",
      "user": 1,
      "content_type": 4,
      "object_id": "CC4456",
      "object_repr": "CC4456 dos",
      "action_flag": 1,
      "change_message": "[{\"added\": {}}]"
    }
  },
  {
    "model": "admin.logentry",
    "pk": 6,
    "fields": {
      "action_time": "2019-05-05T23:37:20.077Z",
      "user": 1,
      "content_type": 5,
      "object_id": "1",
      "object_repr": "Evaluacion: 1",
      "action_flag": 1,
      "change_message": "[{\"added\": {}}]"
    }
  },
  {
    "model": "admin.logentry",
    "pk": 7,
    "fields": {
      "action_time": "2019-05-05T23:37:37.265Z",
      "user": 1,
      "content_type": 5,
      "object_id": "2",
      "object_repr": "Evaluacion: 2",
      "action_flag": 1,
      "change_message": "[{\"added\": {}}]"
    }
  },
  {
    "model": "admin.logentry",
    "pk": 8,
    "fields": {
      "action_time": "2019-05-05T23:37:51.118Z",
      "user": 1,
      "content_type": 7,
      "object_id": "1",
      "object_repr": "Evaluacion: Evaluacion: 1 Rubrica: CC4301 Oto\u00f1o 2018",
      "action_flag": 1,
      "change_message": "[{\"added\": {}}]"
    }
  },
  {
    "model": "admin.logentry",
    "pk": 9,
    "fields": {
      "action_time": "2019-05-05T23:38:03.803Z",
      "user": 1,
      "content_type": 6,
      "object_id": "1",
      "object_repr": "User: bla@bla.cl Evaluation: Evaluacion: 1",
      "action_flag": 1,
      "change_message": "[{\"added\": {}}]"
    }
  },
  {
    "model": "admin.logentry",
    "pk": 10,
    "fields": {
      "action_time": "2019-05-05T23:38:09.281Z",
      "user": 1,
      "content_type": 6,
      "object_id": "2",
      "object_repr": "User: eval1@eval.cl Evaluation: Evaluacion: 2",
      "action_flag": 1,
      "change_message": "[{\"added\": {}}]"
    }
  },
  {
    "model": "admin.logentry",
    "pk": 11,
    "fields": {
      "action_time": "2019-05-05T23:38:16.140Z",
      "user": 1,
      "content_type": 6,
      "object_id": "3",
      "object_repr": "User: eval3@eval.cl Evaluation: Evaluacion: 2",
      "action_flag": 1,
      "change_message": "[{\"added\": {}}]"
    }
  },
  {
    "model": "admin.logentry",
    "pk": 12,
    "fields": {
      "action_time": "2019-05-05T23:38:28.540Z",
      "user": 1,
      "content_type": 8,
      "object_id": "1",
      "object_repr": "Curso: Logaritmos CC3451 Oto\u00f1o 2018 1 Evaluacion: Evaluacion: 1",
      "action_flag": 1,
      "change_message": "[{\"added\": {}}]"
    }
  },
  {
    "model": "admin.logentry",
    "pk": 13,
    "fields": {
      "action_time": "2019-05-05T23:38:35.454Z",
      "user": 1,
      "content_type": 8,
      "object_id": "2",
      "object_repr": "Curso: Ingenieria CC3410 Oto\u00c3\u00b1o 2019 1 Evaluacion: Evaluacion: 2",
      "action_flag": 1,
      "change_message": "[{\"added\": {}}]"
    }
  },
  {
    "model": "admin.logentry",
    "pk": 14,
    "fields": {
      "action_time": "2019-05-05T23:39:46.070Z",
      "user": 1,
      "content_type": 9,
      "object_id": "1",
      "object_repr": "No Group",
      "action_flag": 1,
      "change_message": "[{\"added\": {}}]"
    }
  },
  {
    "model": "admin.logentry",
    "pk": 15,
    "fields": {
      "action_time": "2019-05-05T23:39:56.200Z",
      "user": 1,
      "content_type": 9,
      "object_id": "2",
      "object_repr": "fsociety",
      "action_flag": 1,
      "change_message": "[{\"added\": {}}]"
    }
  },
  {
    "model": "admin.logentry",
    "pk": 16,
    "fields": {
      "action_time": "2019-05-05T23:40:19.747Z",
      "user": 1,
      "content_type": 9,
      "object_id": "3",
      "object_repr": "fsociety",
      "action_flag": 1,
      "change_message": "[{\"added\": {}}]"
    }
  },
  {
    "model": "admin.logentry",
    "pk": 17,
    "fields": {
      "action_time": "2019-05-05T23:40:53.087Z",
      "user": 1,
      "content_type": 9,
      "object_id": "2",
      "object_repr": "fsociety",
      "action_flag": 2,
      "change_message": "[{\"changed\": {\"fields\": [\"alumnos\"]}}]"
    }
  },
  {
    "model": "admin.logentry",
    "pk": 18,
    "fields": {
      "action_time": "2019-05-05T23:41:11.982Z",
      "user": 1,
      "content_type": 10,
      "object_id": "1",
      "object_repr": "Alumno: 1234567-2 Nota: 6.0 Evaluacion: Evaluacion: 1",
      "action_flag": 1,
      "change_message": "[{\"added\": {}}]"
    }
  },
  {
    "model": "admin.logentry",
    "pk": 19,
    "fields": {
      "action_time": "2019-05-05T23:41:18.834Z",
      "user": 1,
      "content_type": 10,
      "object_id": "2",
      "object_repr": "Alumno: 12342567-5 Nota: 8.0 Evaluacion: Evaluacion: 2",
      "action_flag": 1,
      "change_message": "[{\"added\": {}}]"
    }
  },
  {
    "model": "admin.logentry",
    "pk": 20,
    "fields": {
      "action_time": "2019-05-05T23:42:58.229Z",
      "user": 1,
      "content_type": 14,
      "object_id": "2",
      "object_repr": "dummy",
      "action_flag": 2,
      "change_message": "[{\"changed\": {\"fields\": [\"password\"]}}]"
    }
  }
]